LICENSE
MANIFEST.in
README.rst
buildout.cfg
develop.cfg
requirements.txt
setup.py
version.txt
bob/__init__.py
bob.ip.draw.egg-info/PKG-INFO
bob.ip.draw.egg-info/SOURCES.txt
bob.ip.draw.egg-info/dependency_links.txt
bob.ip.draw.egg-info/not-zip-safe
bob.ip.draw.egg-info/requires.txt
bob.ip.draw.egg-info/top_level.txt
bob/ip/__init__.py
bob/ip/draw/__init__.py
bob/ip/draw/box.cpp
bob/ip/draw/cross.cpp
bob/ip/draw/line.cpp
bob/ip/draw/main.cpp
bob/ip/draw/point.cpp
bob/ip/draw/test.py
bob/ip/draw/try_point.cpp
bob/ip/draw/utils.h
bob/ip/draw/version.cpp
bob/ip/draw/include/bob.ip.draw/config.h
bob/ip/draw/include/bob.ip.draw/drawing.h
doc/conf.py
doc/index.rst
doc/links.rst
doc/py_api.rst