Metadata-Version: 1.1
Name: bob.ip.draw
Version: 2.0.10
Summary: Line and Box drawing utilities of Bob
Home-page: http://gitlab.idiap.ch/bob/bob.ip.draw
Author: Andre Anjos
Author-email: andre.anjos@idiap.ch
License: BSD
Platform: UNKNOWN
Classifier: Framework :: Bob
Classifier: Development Status :: 4 - Beta
Classifier: Intended Audience :: Developers
Classifier: License :: OSI Approved :: BSD License
Classifier: Natural Language :: English
Classifier: Programming Language :: Python
Classifier: Programming Language :: Python :: 3
Classifier: Topic :: Software Development :: Libraries :: Python Modules
